cpuid.py
cpuid-0.0.10.dist-info/LICENSE
cpuid-0.0.10.dist-info/METADATA
cpuid-0.0.10.dist-info/WHEEL
cpuid-0.0.10.dist-info/dependency_links.txt
cpuid-0.0.10.dist-info/top_level.txt
cpuid-0.0.10.dist-info/RECORD
